[{"id_application":"2019河西建证申字0015","name":"住宅重建","provider":"刘义","location_area":"河西区","location_detail":"环湖北道","id_book":"2019河西建证0013","size":"197.95","date_allow":"2019-09-20","date_publish":"2019-09-27"},{"id_application":"2019河西建证申字0003变更01","name":"陈塘科技商务区W2地块","provider":"天津中交绿城城市建设发展有限公司","location_area":"河西区","location_detail":"春海道和东江道交口东南侧","id_book":"2019河西建证0002","size":" ","date_allow":"2019-09-18","date_publish":"2019-09-20"},{"id_application":"2018河西建证申字0014变更01","name":"小海地110千伏变电站重建工程","provider":"国网天津市电力公司城南供电分公司","location_area":"河西区","location_detail":"微山路与双水道交口","id_book":"2018河西建证0012","size":" ","date_allow":"2019-09-05","date_publish":"2019-09-06"},{"id_application":"2019河西建证申字0012","name":"津铁泽苑、津铁和苑、津铁美苑围墙大门","provider":"天津京铁房地产开发有限公司","location_area":"河西区","location_detail":"尖山路两侧","id_book":"2019河西建证0011","size":" ","date_allow":"2019-08-27","date_publish":"2019-09-06"},{"id_application":"2014河西建证申字0045变更01","name":"退休干部安置住房","provider":"中国人民解放军31033部队（原61723部队）","location_area":"河西区","location_detail":"宾馆南道1号","id_book":"2014河西住证0010","size":"9027.85","date_allow":"2019-08-22","date_publish":"2019-08-23"},{"id_application":"2016河西建证申字0039变更06","name":"天津市儿童医院改扩建一期","provider":"天津市人民政府(天津市儿童医院)","location_area":"河西区","location_detail":" ","id_book":"2016河西建证0023","size":" ","date_allow":"2019-07-15","date_publish":"2019-07-22"},{"id_application":"2019河西建证申字0010","name":"郡都大厦围墙大门","provider":"天津亿万泉实业有限公司","location_area":"河西区","location_detail":"洞庭路与怒江道交口","id_book":"2019河西建证0010","size":" ","date_allow":"2019-07-09","date_publish":"2019-07-15"},{"id_application":"2019河西建证申字0008","name":"美克美家天津专卖店改扩建","provider":"美克国际家居用品股份有限公司","location_area":"河西区","location_detail":"解放南路东侧","id_book":"2019河西建证0009","size":"25247","date_allow":"2019-06-28","date_publish":"2019-07-01"},{"id_application":"2019河西建证申字0008","name":"美克美家天津专卖店改扩建","provider":"美克国际家居用品股份有限公司","location_area":"河西区","location_detail":"解放南路东侧","id_book":"2019河西建证0009","size":"25247","date_allow":"2019-06-28","date_publish":"2019-07-01"},{"id_application":"2019河西建证申字0009","name":"六合里围墙大门","provider":"天津天房天陆置业有限公司","location_area":"河西区","location_detail":"黑牛城道与棠海路交口","id_book":"2019河西建证0008","size":" ","date_allow":"2019-06-24","date_publish":"2019-07-01"},{"id_application":"2019河西建证申字0007","name":"陈塘科技商务区3号地块","provider":"天津中交绿城城市建设发展有限公司","location_area":"河西区","location_detail":"内江路与崇江道交口东南角","id_book":"2019河西建证0007","size":"116877.44","date_allow":"2019-06-06","date_publish":"2019-06-14"},{"id_application":"2015河西建证申字0013变更01","name":"天津医科大学肿瘤医院扩建二期北院区门诊医技楼工程","provider":"天津市人民政府（天津市肿瘤医院）","location_area":"河西区","location_detail":"体院北环湖西路","id_book":"2015河西建证0009","size":"39996","date_allow":"2019-05-27","date_publish":"2019-05-31"},{"id_application":"2016河西建证申字0039变更01","name":"天津市儿童医院改扩建一期工程","provider":"天津市人民政府(天津市儿童医院)","location_area":"河西区","location_detail":"马场道225号","id_book":"2016河西建证0023","size":" ","date_allow":"2019-05-13","date_publish":"2019-05-17"},{"id_application":"2015河西建证申字0045变更01","name":"六合里","provider":"天津天房天陆置业有限公司","location_area":"河西区","location_detail":"黑牛城道与洞庭路","id_book":"2015河西住证0018","size":" ","date_allow":"2019-04-30","date_publish":"2019-05-10"},{"id_application":"2015河西建证申字0045变更01","name":"六合里","provider":"天津天房天陆置业有限公司","location_area":"河西区","location_detail":"黑牛城道与洞庭路","id_book":"2015河西住证0018","size":" ","date_allow":"2019-04-30","date_publish":"2019-05-10"},{"id_application":"2019河西建证申字0006","name":"陈塘庄地面沉降分层监测标重建项目","provider":"天津市地质环境监测总站","location_area":"河西区","location_detail":"天津市河西区","id_book":"2019河西建证0006","size":"324","date_allow":"2019-04-28","date_publish":"2019-05-10"},{"id_application":"2019河西建证申字0005","name":"天津银行后台运营中心大楼维修改造项目","provider":"天津银行股份有限公司","location_area":"河西区","location_detail":"天津市河西区友谊路15号","id_book":"2019河西建证0005","size":"31907.1","date_allow":"2019-04-12","date_publish":"2019-04-19"},{"id_application":"2018河西建证申字0008变更01","name":"仁盛花园二期","provider":"天津市晟林房地产开发有限公司","location_area":"河西区","location_detail":"河西区 浯水道和内江路交口东南侧","id_book":"2018河西住证0003","size":" ","date_allow":"2019-04-10","date_publish":"2019-04-12"},{"id_application":"2019河西建证申字0004","name":"河西区解放南路（东侧一区）26号地（居住部分）","provider":"天津佳意房地产开发有限公司","location_area":"河西区","location_detail":"浯水道与沂山路交口东南侧","id_book":"2019河西建证0004","size":" ","date_allow":"2019-02-03","date_publish":"2019-02-03"},{"id_application":"2019河西建证申字0002","name":"解放南路（东侧一区）26号地块（幼儿园）","provider":"天津佳意房地产开发有限公司","location_area":"河西区","location_detail":"梦湖西道与沂山路交口东北侧","id_book":"2019河西建证0003","size":" ","date_allow":"2019-01-29","date_publish":"2019-02-03"},{"id_application":"2019河西建证申字0003","name":"陈塘科技商务区W2地块","provider":"天津中交绿城城市建设发展有限公司","location_area":"河西区","location_detail":"春海道和东江道交口东南侧","id_book":"2019河西建证0002","size":" ","date_allow":"2019-01-28","date_publish":"2019-01-29"},{"id_application":"2019河西建证申字0001","name":"名郡大厦项目围墙工程","provider":"天津渤海恒源房地产开发股份有限公司","location_area":"河西区","location_detail":"郁江道与彭泽道交口","id_book":"2019河西建证0001","size":" ","date_allow":"2019-01-22","date_publish":"2019-01-29"},{"id_application":"2018河西建证申字5002","name":"陈塘科技商务区W1地块","provider":"天津中交绿城城市建设发展有限公司","location_area":"河西区","location_detail":"春海路和双海道交口东南侧","id_book":"2018河西建证5002","size":" ","date_allow":"2018-12-19","date_publish":"2018-12-20"},{"id_application":"2018河西建证申字5001","name":"河西区消防二级指挥中心","provider":"天津市河西区公安消防支队","location_area":"河西区","location_detail":"大沽南路土城消防站现址","id_book":"2018河西建证5001","size":" ","date_allow":"2018-12-14","date_publish":"2018-12-20"},{"id_application":"2018河西建证申字5000","name":"儿童医院增建钢结构门厅项目","provider":"天津市人民政府（天津市儿童医院）","location_area":"河西区","location_detail":"马场道225号","id_book":"2018河西建证5000","size":" ","date_allow":"2018-11-16","date_publish":"2018-11-23"},{"id_application":"2013河西建证申字0041变更","name":"天津市河西区东海街社区卫生服务中心改扩建工程","provider":"天津市人民政府（天津市河西区东海街社区卫生服务中心）","location_area":"河西区","location_detail":"枫林路25号","id_book":"2013河西建证0027","size":"2984.70","date_allow":"2018-10-23","date_publish":"2018-11-07"},{"id_application":"2018河西建证申字0018","name":"三诚里（10号楼）","provider":"天津博雅置业有限公司","location_area":"河西区","location_detail":"黑牛城道与内江北路交口西南侧","id_book":"2018河西建证0016","size":"31515.89","date_allow":"2018-10-23","date_publish":"2018-11-07"},{"id_application":"2016河西建证申字0033变更","name":"三诚里（11号楼）","provider":"天津博雅置业有限公司","location_area":"河西区","location_detail":"黑牛城道与内江北路交口西南侧","id_book":"2016河西建证0021","size":"6365.79","date_allow":"2018-10-15","date_publish":"2018-11-07"},{"id_application":"2018河西建证申字0017","name":"雅湖里围墙大门","provider":"天津瑞鼎置业有限公司","location_area":"河西区","location_detail":"解放南路东侧27号地","id_book":"2018河西建证0015","size":"0","date_allow":"2018-10-15","date_publish":"2018-11-07"},{"id_application":"2018河西建证申字0016","name":"中心城区水环境提升近期工程复兴河口泵站工程","provider":"天津水务投资集团有限公司","location_area":"河西区","location_detail":"复兴河入海河汇合口西北角处","id_book":"2018河西建证0014","size":"240","date_allow":"2018-10-11","date_publish":"2018-11-07"},{"id_application":"2018河西建证申字0015","name":"天津市解放南路地区2#能源站","provider":"天津市管道工程集团通源达科技有限公司","location_area":"河西区","location_detail":"解放南路地区起步区绿轴东侧36号地块内","id_book":"2018河西建证0013","size":"4700","date_allow":"2018-10-09","date_publish":"2018-11-07"},{"id_application":"2018河西建证申字0014","name":"小海地110千伏变电站重建工程","provider":"国网天津市电力公司","location_area":"河西区","location_detail":"微山路与双水道交口","id_book":"2018河西建证0012","size":"1722.45","date_allow":"2018-09-27","date_publish":"2018-10-19"},{"id_application":"2014河西建证申字0013变更","name":"秀竹苑","provider":"天津物产置业发展有限公司","location_area":"河西区","location_detail":"太湖路与郁江道交口的东南侧","id_book":"2014河西住证0003","size":"62257.01","date_allow":"2018-09-25","date_publish":"2018-10-19"},{"id_application":"2014河西建证申字0043变更","name":"丽竹苑","provider":"天津物产置业发展有限公司","location_area":"河西区","location_detail":"幕山路与郁江道交口的东南侧","id_book":"2015河西住证0002","size":"13236.39","date_allow":"2018-09-25","date_publish":"2018-10-19"},{"id_application":"2014河西建证申字0013变更","name":"秀竹苑","provider":"天津物产置业发展有限公司","location_area":"河西区","location_detail":"太湖路与郁江道交口的东南侧","id_book":"2014河西住证0003","size":"62257.01","date_allow":"2018-09-25","date_publish":"2018-10-19"},{"id_application":"2014河西建证申字0043变更","name":"丽竹苑","provider":"天津物产置业发展有限公司","location_area":"河西区","location_detail":"幕山路与郁江道交口的东南侧","id_book":"2015河西住证0002","size":"13236.39","date_allow":"2018-09-25","date_publish":"2018-10-19"},{"id_application":"2018河西建证申字0003变更","name":"渌水道501号幼儿园围墙及大门","provider":"天津绿城全运村建设开发有限公司","location_area":"河西区","location_detail":"林海路与渌水道交口西南侧","id_book":"2018河西建证0002","size":"0","date_allow":"2018-09-20","date_publish":"2018-10-19"},{"id_application":"2017河西建证申字0026变更","name":"棣棠园围墙、大门","provider":"天津绿城全运村建设开发有限公司","location_area":"河西区","location_detail":"渌水道南侧","id_book":"2017河西建证0019","size":"0","date_allow":"2018-09-20","date_publish":"2018-10-19"},{"id_application":"2015河西建证申字0010变更","name":"津雅苑","provider":"天津立达房地产投资有限公司","location_area":"河西区","location_detail":"叠彩道北侧","id_book":"2015河西住证0003","size":"48025.80","date_allow":"2018-09-13","date_publish":"2018-10-19"},{"id_application":"2015河西建证申字0010变更","name":"津雅苑","provider":"天津立达房地产投资有限公司","location_area":"河西区","location_detail":"叠彩道北侧","id_book":"2015河西住证0003","size":"48025.80","date_allow":"2018-09-13","date_publish":"2018-10-19"},{"id_application":"2018河西建证申字0013","name":"天津外国语大学马场道校区10KV变电站扩容改造","provider":"天津外国语大学","location_area":"河西区","location_detail":"马场道117号内","id_book":"2018河西建证0011","size":"217.91","date_allow":"2018-09-11","date_publish":"2018-10-19"},{"id_application":"2016河西建证申字0044变更","name":"天津市第四中学迁址扩建二期工程","provider":"天津市河西区教育局","location_area":"河西区","location_detail":"尖山八大里地区金星里地块","id_book":"2016河西建证0029","size":"6470.30","date_allow":"2018-09-10","date_publish":"2018-10-19"},{"id_application":"2016河西建证申字0020变更","name":"天津市第四中学迁址扩建工程","provider":"天津市河西区教育局","location_area":"河西区","location_detail":"尖山八大里地区金星里地块","id_book":"2016河西建证0013","size":"45690.60","date_allow":"2018-09-10","date_publish":"2018-10-19"},{"id_application":"2015河西建证申字0037变更","name":"天津陈塘科技商务区1-2号地块（安融大厦）","provider":"天津融商投资有限公司","location_area":"河西区","location_detail":"洞庭路西侧","id_book":"2015河西建证0020","size":"60821.79","date_allow":"2018-09-03","date_publish":"2018-10-19"},{"id_application":"2016河西建证申字0022变更","name":"六合大厦、六合公寓","provider":"天津天房天陆置业有限公司","location_area":"河西区","location_detail":"黑牛城道与洞庭路交口西北侧","id_book":"2016河西建证0016","size":"208000","date_allow":"2018-08-23","date_publish":"2018-09-30"},{"id_application":"2015河西建证申字0045变更","name":"六合里","provider":"天津天房天陆置业有限公司","location_area":"河西区","location_detail":"黑牛城道与洞庭路交口西北侧","id_book":"2015河西住证0018","size":"158000","date_allow":"2018-08-16","date_publish":"2018-09-30"},{"id_application":"2018河西建证申字0012","name":"河西区第一幼儿园分园围墙大门","provider":"天津瑞鼎置业有限公司","location_area":"河西区","location_detail":"解放南路东侧27号地内","id_book":"2018河西建证0010","size":"0","date_allow":"2018-08-10","date_publish":"2018-09-30"},{"id_application":"2015河西建证申字0028变更","name":"清湖花园二期","provider":"天津豪廷房地产开发有限公司","location_area":"河西区","location_detail":"太湖路与内江路交口西南侧","id_book":"2015河西住证0010","size":"68962.49","date_allow":"2018-08-08","date_publish":"2018-09-30"},{"id_application":"2015河西建证申字0028变更","name":"清湖花园二期","provider":"天津豪廷房地产开发有限公司","location_area":"河西区","location_detail":"太湖路与内江路交口西南侧","id_book":"2015河西住证0010","size":"68962.49","date_allow":"2018-08-08","date_publish":"2018-09-30"},{"id_application":"2018河西建证申字0010","name":"融邦大厦","provider":"天津市房地产发展（集团）股份有限公司","location_area":"河西区","location_detail":"友谊北路","id_book":"2018河西建证0009","size":"52064.54","date_allow":"2018-08-07","date_publish":"2018-09-30"},{"id_application":"2018河西建证申字0011","name":"锦葵园配建2、配建3大门及围墙","provider":"天津绿城全运村建设开发有限公司","location_area":"河西区","location_detail":"梅林路东侧","id_book":"2018河西建证0008","size":"0","date_allow":"2018-08-02","date_publish":"2018-09-30"},{"id_application":"2017河西建证申字0012变更","name":"解放南路（东侧三区）林海路绿地公园地块","provider":"天津绿城全运村建设开发有限公司","location_area":"河西区","location_detail":"林海路与渌水道交口东南侧","id_book":"2017河西建证0011","size":"200","date_allow":"2018-08-02","date_publish":"2018-09-30"},{"id_application":"2017河西建证申字0017变更","name":"五福里16号楼及配建一","provider":"天津中海海盛地产有限公司","location_area":"河西区","location_detail":"黑牛城道与洞庭路交口东南侧","id_book":"2017河西住证0004","size":"8981.50","date_allow":"2018-07-23","date_publish":"2018-08-31"},{"id_application":"2016河西建证申字0034变更","name":"浙昆大厦二期（办公楼、酒店、商业及地下室）","provider":"天津昆仑兆业投资有限公司","location_area":"河西区","location_detail":"湛江路20号","id_book":"2016河西建证0022","size":"95685","date_allow":"2018-07-11","date_publish":"2018-08-31"},{"id_application":"2016河西建证申字0034变更","name":"浙昆大厦二期（办公楼、酒店、商业及地下室）","provider":"天津昆仑兆业投资有限公司","location_area":"河西区","location_detail":"湛江路20号","id_book":"2016河西建证0022","size":"95685","date_allow":"2018-07-11","date_publish":"2018-08-31"},{"id_application":"2016河西建证申字0037变更","name":"津铁泽苑","provider":"天津京铁房地产开发公司","location_area":"河西区","location_detail":"河西区黑牛城道陈塘庄铁路货场","id_book":"2016河西住证0011","size":"282786.69","date_allow":"2018-07-05","date_publish":"2018-08-31"},{"id_application":"2017河西建证申字0007变更","name":"新八大里片区五里小学","provider":"天津城投置地投资发展有限公司","location_area":"河西区","location_detail":"五福里地块内","id_book":"2017河西建证0007","size":"11970","date_allow":"2018-06-07","date_publish":"2018-07-09"},{"id_application":"2018河西建证申字0008","name":"仁盛花园二期","provider":"天津市晟林房地产开发有限公司","location_area":"河西区","location_detail":"浯水道和内江路交口东南侧","id_book":"2018河西住证0003","size":"125609.39","date_allow":"2018-05-29","date_publish":"2018-07-09"},{"id_application":"2018河西建证申字0007","name":"五福里配建一围墙","provider":"天津中海海盛地产有限公司","location_area":"河西区","location_detail":"嘉江道与沐江道交口东南侧","id_book":"2018河西建证0006","size":"0","date_allow":"2018-05-22","date_publish":"2018-07-09"},{"id_application":"2018河西建证申字0006","name":"解放南路615号（解放南路汽车园项目南侧绿地）","provider":"天津市环渤海汽车市场有限公司","location_area":"河西区","location_detail":"解放南路东侧","id_book":"2018河西建证0005","size":"100","date_allow":"2018-05-04","date_publish":"2018-07-09"},{"id_application":"2016河西建证申字0041变更","name":"五福里5-8号楼及地下车库二","provider":"天津中海海盛地产有限公司","location_area":"河西区","location_detail":"黑牛城道与洞庭路交口东南侧","id_book":"2016河西建证0026","size":"58781.64","date_allow":"2018-04-26","date_publish":"2018-05-30"},{"id_application":"2018河西建证申字0005","name":"天津师范大学第二附属小学（渌水道校区）综合楼改扩建项目","provider":"天津市河西区住宅配套办公室","location_area":"河西区","location_detail":"渌水道与枫林路交叉口","id_book":"2018河西建证0004","size":"2010.31","date_allow":"2018-04-26","date_publish":"2018-05-30"},{"id_application":"2018河西建证申字0004","name":"仁盛花园一期","provider":"天津市晟林房地产开发有限公司","location_area":"河西区","location_detail":"浯水道和内江路交口东南侧","id_book":"2018河西住证0002","size":"35490.61","date_allow":"2018-04-24","date_publish":"2018-05-30"},{"id_application":"2018河西建证申字0002","name":"榆林路365号小学围墙及大门","provider":"天津绿城全运村建设开发有限公司","location_area":"河西区","location_detail":"淇水道与榆林路交口东南角","id_book":"2018河西建证0003","size":"0","date_allow":"2018-04-20","date_publish":"2018-05-30"},{"id_application":"2018河西建证申字0003","name":"渌水道501号幼儿园围墙及大门","provider":"天津绿城全运村建设开发有限公司","location_area":"河西区","location_detail":"林海路与渌水道交口西南侧","id_book":"2018河西建证0002","size":"0","date_allow":"2018-04-20","date_publish":"2018-05-30"},{"id_application":"2017河西建证申字0010变更","name":"五福里14、15号楼及配建四、配建七及地下车库四、地下车库七","provider":"天津中海海盛地产有限公司","location_area":"河西区","location_detail":"黑牛城道与洞庭路交口东南角","id_book":"2017河西住证0001","size":"13344.58","date_allow":"2018-04-10","date_publish":"2018-05-30"},{"id_application":"2016河西建证申字0026变更","name":"天津市第二实验中学","provider":"天津城投置地投资发展有限公司","location_area":"河西区","location_detail":"东海街道梅林路与淇水道交口","id_book":"2016河西建证0017","size":"33000","date_allow":"2018-03-23","date_publish":"2018-04-25"},{"id_application":"2016河西建证申字0040变更","name":"解放南路地区起步区39号地公交首末站","provider":"天津城投置地投资发展有限公司","location_area":"河西区","location_detail":"解放南路地区39号地內","id_book":"2016河西建证0025","size":"895","date_allow":"2018-03-19","date_publish":"2018-04-25"},{"id_application":"2015河西建证申字0015变更","name":"双迎里（含城市广场）","provider":"天津渤海置业有限公司","location_area":"河西区","location_detail":"太湖路与黑牛城道交口东南角","id_book":"2015河西住证0011","size":"112400","date_allow":"2018-03-05","date_publish":"2018-04-25"},{"id_application":"2015河西建证申字0016变更","name":"双迎公寓（一期）、双迎大厦","provider":"天津渤海置业有限公司","location_area":"河西区","location_detail":"太湖路与黑牛城道交口东南角","id_book":"2015河西建证0012","size":"87469.50","date_allow":"2018-03-05","date_publish":"2018-04-25"},{"id_application":"2015河西建证申字0015变更","name":"双迎里（含城市广场）","provider":"天津渤海置业有限公司","location_area":"河西区","location_detail":"太湖路与黑牛城道交口东南角","id_book":"2015河西住证0011","size":"112400","date_allow":"2018-03-05","date_publish":"2018-04-25"},{"id_application":"2015河西建证申字0016变更","name":"双迎公寓（一期）、双迎大厦","provider":"天津渤海置业有限公司","location_area":"河西区","location_detail":"太湖路与黑牛城道交口东南角","id_book":"2015河西建证0012","size":"87469.50","date_allow":"2018-03-05","date_publish":"2018-04-25"},{"id_application":"2013河西建证申字0007变更","name":"颐航大厦","provider":"中交第一航务工程勘察设计院有限公司","location_area":"河西区","location_detail":"洞庭路与双海道（现名东江道）交口","id_book":"2013河西建证0006","size":"39710","date_allow":"2018-02-08","date_publish":"2018-03-23"},{"id_application":"2016河西建证申字0010变更","name":"五福大厦及地下车库五","provider":"天津中海海盛地产有限公司","location_area":"河西区","location_detail":"黑牛城道与洞庭路交口东南侧","id_book":"2016河西建证0009","size":"57500","date_allow":"2018-01-18","date_publish":"2018-02-09"},{"id_application":"2017河西建证申字0030","name":"平泰大厦","provider":"天津市美银房地产开发有限公司","location_area":"河西区","location_detail":"马场道与合肥道交口","id_book":"2018河西建证0001","size":"233636.40","date_allow":"2018-01-02","date_publish":"2018-02-09"},{"id_application":"2015河西建证申字0049变更","name":"七贤南里（D地块）","provider":"天津中冶名泰置业有限公司","location_area":"河西区","location_detail":"泽庭道与观海路交口东南侧","id_book":"2015河西建证0031","size":"84000","date_allow":"2017-12-26","date_publish":"2018-01-29"},{"id_application":"2016河西建证申字0028变更","name":"七贤南里（C地块）","provider":"天津中冶名泰置业有限公司","location_area":"河西区","location_detail":"泽庭道与观海路交口西南侧","id_book":"2016河西建证0019","size":"114000","date_allow":"2017-12-26","date_publish":"2018-01-29"},{"id_application":"2015河西建证申字0049变更","name":"七贤南里（D地块）","provider":"天津中冶名泰置业有限公司","location_area":"河西区","location_detail":"泽庭道与观海路交口东南侧","id_book":"2015河西建证0031","size":"84000","date_allow":"2017-12-26","date_publish":"2018-01-29"},{"id_application":"2016河西建证申字0028变更","name":"七贤南里（C地块）","provider":"天津中冶名泰置业有限公司","location_area":"河西区","location_detail":"泽庭道与观海路交口西南侧","id_book":"2016河西建证0019","size":"114000","date_allow":"2017-12-26","date_publish":"2018-01-29"},{"id_application":"2015河西建证申字0027变更","name":"三诚里（2-9、12-25号楼）","provider":"天津博雅置业有限公司","location_area":"河西区","location_detail":"黑牛城道与洪泽南路交口东南侧","id_book":"2015河西建证0014","size":"193040.69","date_allow":"2017-12-18","date_publish":"2018-01-29"},{"id_application":"2014河西建证申字0031变更","name":"解放南路地区起步区39号地垃圾转运站（含环卫基层机构）及围墙、大门","provider":"天津城投置地投资发展有限公司","location_area":"河西区","location_detail":"解放南路东侧39号地内","id_book":"2014河西建证0027","size":"2400","date_allow":"2017-11-14","date_publish":"2017-12-20"},{"id_application":"2015河西建证申字0005变更","name":"海景文苑14-18号楼","provider":"天津海景实业有限公司","location_area":"河西区","location_detail":"台儿庄南路与古海路交口","id_book":"2015河西建证0004","size":"102097.70","date_allow":"2017-10-31","date_publish":"2017-11-17"},{"id_application":"2015河西建证申字0005变更","name":"海景文苑14-18号楼","provider":"天津海景实业有限公司","location_area":"河西区","location_detail":"台儿庄南路与古海路交口","id_book":"2015河西建证0004","size":"102097.70","date_allow":"2017-10-31","date_publish":"2017-11-17"},{"id_application":"2017河西建证申字0029","name":"第五营销分公司搬迁工程","provider":"天津市自来水集团有限公司","location_area":"河西区","location_detail":"洞庭路与浯水道交口","id_book":"2017河西建证0022","size":"5958.86","date_allow":"2017-10-30","date_publish":"2017-11-17"},{"id_application":"2016河西建证申字0027变更","name":"益发里（1-7号楼）","provider":"天津天地源唐城房地产开发有限公司","location_area":"河西区","location_detail":"沐江道南侧、太湖路西侧","id_book":"2016河西住证0008","size":"37400","date_allow":"2017-09-19","date_publish":"2017-11-10"},{"id_application":"2016河西建证申字0019变更","name":"七贤南里B地块","provider":"天津中冶名泰置业有限公司","location_area":"河西区","location_detail":"泽庭道与观海路交口西南侧","id_book":"2016河西住证0007","size":"64394.18","date_allow":"2017-09-18","date_publish":"2017-11-10"}]